assertshape/__init__.py
assertshape/assertshape.py
assertshape/test_assertshape.py
assertshape-0.0.1.dist-info/METADATA
assertshape-0.0.1.dist-info/WHEEL
assertshape-0.0.1.dist-info/licenses/LICENSE
assertshape-0.0.1.dist-info/RECORD
