Metadata-Version: 2.1
Name: assertshape
Version: 0.0.1
Summary: Utility for checking n-dim array shapes using Einstein notation.
Project-URL: Homepage, https://github.com/steinwaywhw/assertshape
Project-URL: Bug Tracker, https://github.com/steinwaywhw/assertshape/issues
Author-email: Steinway Wu <steinwaywhw@gmail.com>
License: MIT License
Classifier: License :: OSI Approved :: MIT License
Classifier: Operating System :: OS Independent
Classifier: Programming Language :: Python :: 3
Requires-Python: >=3
